pytest_yamlwsgi
