Metadata-Version: 1.0
Name: pytest-yamlwsgi
Version: 0.6
Summary: Run tests against wsgi apps defined in yaml
Home-page: UNKNOWN
Author: Ali Afshar
Author-email: aafshar@gmail.com
License: UNKNOWN
Platform: UNKNOWN
